<annotation>
	<folder>菜刀</folder>
	<filename>cd420.jpg</filename>
	<path>C:\Users\TN\Desktop\untitled1\菜刀\cd420.jpg</path>
	<source>
		<database>Unknown</database>
	</source>
	<size>
		<width>150</width>
		<height>150</height>
		<depth>3</depth>
	</size>
	<segmented>0</segmented>
	<object>
		<name>knief</name>
		<pose>Unspecified</pose>
		<truncated>0</truncated>
		<difficult>0</difficult>
		<bndbox>
			<xmin>17</xmin>
			<ymin>36</ymin>
			<xmax>147</xmax>
			<ymax>125</ymax>
		</bndbox>
	</object>
</annotation>
