<annotation>
	<folder>knife</folder>
	<filename>486.jpg</filename>
	<path>C:\Users\TN\Desktop\untitled1\knife\486.jpg</path>
	<source>
		<database>Unknown</database>
	</source>
	<size>
		<width>350</width>
		<height>350</height>
		<depth>3</depth>
	</size>
	<segmented>0</segmented>
	<object>
		<name>knief</name>
		<pose>Unspecified</pose>
		<truncated>0</truncated>
		<difficult>0</difficult>
		<bndbox>
			<xmin>13</xmin>
			<ymin>9</ymin>
			<xmax>327</xmax>
			<ymax>68</ymax>
		</bndbox>
	</object>
	<object>
		<name>knief</name>
		<pose>Unspecified</pose>
		<truncated>0</truncated>
		<difficult>0</difficult>
		<bndbox>
			<xmin>18</xmin>
			<ymin>286</ymin>
			<xmax>342</xmax>
			<ymax>343</ymax>
		</bndbox>
	</object>
</annotation>
